[
  {
    "name": "Massachusetts Institute of Technology (MIT)",
    "website": "https://web.mit.edu"
  },
  {
    "name": "Imperial College London",
    "website": "https://www.imperial.ac.uk"
  },
  {
    "name": "University of Oxford",
    "website": "https://www.ox.ac.uk"
  },
  {
    "name": "Harvard University",
    "website": "https://www.harvard.edu"
  },
  {
    "name": "University of Cambridge",
    "website": "https://www.cam.ac.uk"
  },
  {
    "name": "Stanford University",
    "website": "https://www.stanford.edu"
  },
  {
    "name": "ETH Zurich - Swiss Federal Institute of Technology",
    "website": "https://ethz.ch"
  },
  {
    "name": "National University of Singapore (NUS)",
    "website": "https://www.nus.edu.sg"
  },
  {
    "name": "UCL",
    "website": "https://www.ucl.ac.uk"
  },
  {
    "name": "California Institute of Technology (Caltech)",
    "website": "https://www.caltech.edu"
  },
  {
    "name": "University of Pennsylvania",
    "website": "https://www.upenn.edu"
  },
  {
    "name": "University of California, Berkeley (UCB)",
    "website": "https://www.berkeley.edu"
  },
  {
    "name": "The University of Melbourne",
    "website": "https://www.unimelb.edu.au"
  },
  {
    "name": "Peking University",
    "website": "https://english.pku.edu.cn"
  },
  {
    "name": "Nanyang Technological University, Singapore (NTU)",
    "website": "https://www.ntu.edu.sg"
  },
  {
    "name": "Cornell University",
    "website": "https://www.cornell.edu"
  },
  {
    "name": "The University of Hong Kong",
    "website": "https://www.hku.hk"
  },
  {
    "name": "The University of Sydney",
    "website": "https://www.sydney.edu.au"
  },
  {
    "name": "The University of New South Wales (UNSW Sydney)",
    "website": "https://www.unsw.edu.au"
  },
  {
    "name": "Tsinghua University",
    "website": "https://www.tsinghua.edu.cn"
  },
  {
    "name": "University of Chicago",
    "website": "https://www.uchicago.edu"
  },
  {
    "name": "Princeton University",
    "website": "https://www.princeton.edu"
  },
  {
    "name": "Yale University",
    "website": "https://www.yale.edu"
  },
  {
    "name": "Université PSL",
    "website": "https://www.universite-psl.fr"
  },
  {
    "name": "University of Toronto",
    "website": "https://www.utoronto.ca"
  },
  {
    "name": "EPFL",
    "website": "https://www.epfl.ch"
  },
  {
    "name": "The University of Edinburgh",
    "website": "https://www.ed.ac.uk"
  },
  {
    "name": "Technical University of Munich",
    "website": "https://www.tum.de"
  },
  {
    "name": "McGill University",
    "website": "https://www.mcgill.ca"
  },
  {
    "name": "The Australian National University",
    "website": "https://www.anu.edu.au"
  },
  {
    "name": "Seoul National University",
    "website": "https://www.snu.ac.kr"
  },
  {
    "name": "Johns Hopkins University",
    "website": "https://www.jhu.edu"
  },
  {
    "name": "The University of Tokyo",
    "website": "https://www.u-tokyo.ac.jp"
  },
  {
    "name": "Columbia University",
    "website": "https://www.columbia.edu"
  },
  {
    "name": "The University of Manchester",
    "website": "https://www.manchester.ac.uk"
  },
  {
    "name": "The Chinese University of Hong Kong (CUHK)",
    "website": "https://www.cuhk.edu.hk"
  },
  {
    "name": "Monash University",
    "website": "https://www.monash.edu"
  },
  {
    "name": "University of British Columbia",
    "website": "https://www.ubc.ca"
  },
  {
    "name": "Fudan University",
    "website": "https://www.fudan.edu.cn"
  },
  {
    "name": "King’s College London",
    "website": "https://www.kcl.ac.uk"
  },
  {
    "name": "The University of Queensland",
    "website": "https://www.uq.edu.au"
  },
  {
    "name": "University of California, Los Angeles (UCLA)",
    "website": "https://www.ucla.edu"
  },
  {
    "name": "New York University (NYU)",
    "website": "https://www.nyu.edu"
  },
  {
    "name": "University of Michigan–Ann Arbor",
    "website": "https://umich.edu"
  },
  {
    "name": "Shanghai Jiao Tong University",
    "website": "https://www.sjtu.edu.cn"
  },
  {
    "name": "Institut Polytechnique de Paris",
    "website": "https://www.ip-paris.fr"
  },
  {
    "name": "The Hong Kong University of Science and Technology",
    "website": "https://www.ust.hk"
  },
  {
    "name": "Zhejiang University",
    "website": "https://zju.edu.cn"
  },
  {
    "name": "Delft University of Technology",
    "website": "https://www.tudelft.nl"
  },
  {
    "name": "Kyoto University",
    "website": "https://www.kyoto-u.ac.jp"
  },
  {
    "name": "Northwestern University",
    "website": "https://www.northwestern.edu"
  },
  {
    "name": "The London School of Economics and Political Science (LSE)",
    "website": "https://www.lse.ac.uk"
  },
  {
    "name": "KAIST - Korea Advanced Institute of Science & Technology",
    "website": "https://www.kaist.ac.kr"
  },
  {
    "name": "University of Bristol",
    "website": "https://www.bristol.ac.uk"
  },
  {
    "name": "University of Amsterdam",
    "website": "https://www.uva.nl"
  },
  {
    "name": "Yonsei University",
    "website": "https://www.yonsei.ac.kr"
  },
  {
    "name": "The Hong Kong Polytechnic University",
    "website": "https://www.polyu.edu.hk"
  },
  {
    "name": "Carnegie Mellon University",
    "website": "https://www.cmu.edu"
  },
  {
    "name": "Ludwig-Maximilians-Universität München",
    "website": "https://www.uni-muenchen.de"
  },
  {
    "name": "Universiti Malaya (UM)",
    "website": "https://www.um.edu.my"
  },
  {
    "name": "Duke University",
    "website": "https://www.duke.edu"
  },
  {
    "name": "City University of Hong Kong",
    "website": "https://www.cityu.edu.hk"
  },
  {
    "name": "KU Leuven",
    "website": "https://www.kuleuven.be"
  },
  {
    "name": "Sorbonne University",
    "website": "https://www.sorbonne-universite.fr"
  },
  {
    "name": "The University of Auckland",
    "website": "https://www.auckland.ac.nz"
  },
  {
    "name": "University of Texas at Austin",
    "website": "https://www.utexas.edu"
  },
  {
    "name": "Korea University",
    "website": "https://www.korea.ac.kr"
  },
  {
    "name": "National Taiwan University (NTU)",
    "website": "https://www.ntu.edu.tw"
  },
  {
    "name": "The University of Warwick",
    "website": "https://warwick.ac.uk"
  },
  {
    "name": "University of Illinois at Urbana–Champaign",
    "website": "https://illinois.edu"
  },
  {
    "name": "Universidad de Buenos Aires (UBA)",
    "website": "https://www.uba.ar"
  },
  {
    "name": "University of California, San Diego (UCSD)",
    "website": "https://www.ucsd.edu"
  },
  {
    "name": "Université Paris-Saclay",
    "website": "https://www.universite-paris-saclay.fr"
  },
  {
    "name": "KTH Royal Institute of Technology",
    "website": "https://www.kth.se"
  },
  {
    "name": "Lund University",
    "website": "https://www.lunduniversity.lu.se"
  },
  {
    "name": "University of Washington",
    "website": "https://www.washington.edu"
  },
  {
    "name": "The University of Western Australia",
    "website": "https://www.uwa.edu.au"
  },
  {
    "name": "University of Glasgow",
    "website": "https://www.gla.ac.uk"
  },
  {
    "name": "Brown University",
    "website": "https://www.brown.edu"
  },
  {
    "name": "University of Birmingham",
    "website": "https://www.birmingham.ac.uk"
  },
  {
    "name": "University of Southampton",
    "website": "https://www.southampton.ac.uk"
  },
  {
    "name": "The University of Adelaide",
    "website": "https://www.adelaide.edu.au"
  },
  {
    "name": "University of Leeds",
    "website": "https://www.leeds.ac.uk"
  },
  {
    "name": "Ruprecht-Karls-Universität Heidelberg",
    "website": "https://www.uni-heidelberg.de"
  },
  {
    "name": "Tokyo Institute of Technology (Tokyo Tech)",
    "website": "https://www.titech.ac.jp"
  },
  {
    "name": "Osaka University",
    "website": "https://www.osaka-u.ac.jp"
  },
  {
    "name": "Trinity College Dublin, The University of Dublin",
    "website": "https://www.tcd.ie"
  },
  {
    "name": "University of Technology Sydney",
    "website": "https://www.uts.edu.au"
  },
  {
    "name": "Durham University",
    "website": "https://www.dur.ac.uk"
  },
  {
    "name": "Pennsylvania State University",
    "website": "https://www.psu.edu"
  },
  {
    "name": "Purdue University",
    "website": "https://www.purdue.edu"
  },
  {
    "name": "Universidade de São Paulo",
    "website": "https://www5.usp.br"
  },
  {
    "name": "Pontificia Universidad Católica de Chile (UC)",
    "website": "https://www.uc.cl"
  },
  {
    "name": "Lomonosov Moscow State University",
    "website": "https://www.msu.ru"
  },
  {
    "name": "Universidad Nacional Autónoma de México (UNAM)",
    "website": "https://www.unam.mx"
  },
  {
    "name": "University of Alberta",
    "website": "https://www.ualberta.ca"
  },
  {
    "name": "Freie Universitaet Berlin",
    "website": "https://www.fu-berlin.de"
  },
  {
    "name": "Pohang University of Science And Technology (POSTECH)",
    "website": "https://www.postech.ac.kr"
  },
  {
    "name": "RWTH Aachen University",
    "website": "https://www.rwth-aachen.de"
  },
  {
    "name": "University of Copenhagen",
    "website": "https://www.ku.dk"
  }
]
